<?xml version="1.0" encoding="utf-8" standalone="yes"?>
<Gesture Name="x02" Subject="10" Speed="medium" Number="2" NumPts="55" Millseconds="744" AppName="Gestures" AppVer="3.7.0.0" Date="Wednesday, March 14, 2007" TimeOfDay="11:44:47 AM">
  <Point X="75" Y="171" T="252676268" />
  <Point X="77" Y="169" T="252676315" />
  <Point X="80" Y="171" T="252676327" />
  <Point X="82" Y="172" T="252676336" />
  <Point X="85" Y="174" T="252676343" />
  <Point X="89" Y="177" T="252676351" />
  <Point X="92" Y="180" T="252676359" />
  <Point X="94" Y="182" T="252676365" />
  <Point X="99" Y="186" T="252676372" />
  <Point X="101" Y="188" T="252676378" />
  <Point X="104" Y="191" T="252676379" />
  <Point X="106" Y="193" T="252676387" />
  <Point X="108" Y="195" T="252676388" />
  <Point X="113" Y="201" T="252676395" />
  <Point X="117" Y="207" T="252676403" />
  <Point X="121" Y="213" T="252676411" />
  <Point X="124" Y="220" T="252676420" />
  <Point X="127" Y="225" T="252676428" />
  <Point X="130" Y="231" T="252676437" />
  <Point X="132" Y="236" T="252676446" />
  <Point X="134" Y="240" T="252676455" />
  <Point X="137" Y="247" T="252676464" />
  <Point X="138" Y="249" T="252676474" />
  <Point X="140" Y="251" T="252676487" />
  <Point X="141" Y="249" T="252676520" />
  <Point X="141" Y="247" T="252676530" />
  <Point X="141" Y="244" T="252676540" />
  <Point X="142" Y="240" T="252676551" />
  <Point X="142" Y="233" T="252676561" />
  <Point X="142" Y="225" T="252676573" />
  <Point X="142" Y="220" T="252676584" />
  <Point X="142" Y="218" T="252676585" />
  <Point X="141" Y="210" T="252676597" />
  <Point X="140" Y="201" T="252676609" />
  <Point X="139" Y="194" T="252676621" />
  <Point X="139" Y="190" T="252676633" />
  <Point X="137" Y="181" T="252676646" />
  <Point X="136" Y="176" T="252676659" />
  <Point X="136" Y="173" T="252676672" />
  <Point X="136" Y="169" T="252676673" />
  <Point X="136" Y="166" T="252676687" />
  <Point X="136" Y="164" T="252676700" />
  <Point X="137" Y="162" T="252676716" />
  <Point X="136" Y="165" T="252676783" />
  <Point X="135" Y="168" T="252676797" />
  <Point X="130" Y="178" T="252676816" />
  <Point X="122" Y="186" T="252676836" />
  <Point X="113" Y="195" T="252676856" />
  <Point X="101" Y="206" T="252676876" />
  <Point X="92" Y="216" T="252676893" />
  <Point X="83" Y="225" T="252676910" />
  <Point X="76" Y="232" T="252676927" />
  <Point X="71" Y="237" T="252676944" />
  <Point X="68" Y="241" T="252676960" />
  <Point X="70" Y="239" T="252677012" />
</Gesture>