<?xml version="1.0" encoding="utf-8" standalone="yes"?>
<Gesture Name="v07" Subject="9" Speed="medium" Number="7" NumPts="37" Millseconds="436" AppName="Gestures" AppVer="3.7.0.0" Date="Tuesday, March 13, 2007" TimeOfDay="3:05:25 PM">
  <Point X="80" Y="176" T="201656143" />
  <Point X="81" Y="178" T="201656200" />
  <Point X="82" Y="181" T="201656208" />
  <Point X="83" Y="185" T="201656217" />
  <Point X="86" Y="189" T="201656224" />
  <Point X="87" Y="191" T="201656230" />
  <Point X="88" Y="194" T="201656236" />
  <Point X="90" Y="197" T="201656237" />
  <Point X="91" Y="199" T="201656243" />
  <Point X="94" Y="205" T="201656250" />
  <Point X="97" Y="211" T="201656257" />
  <Point X="98" Y="215" T="201656264" />
  <Point X="99" Y="218" T="201656265" />
  <Point X="101" Y="225" T="201656272" />
  <Point X="102" Y="230" T="201656281" />
  <Point X="103" Y="236" T="201656289" />
  <Point X="103" Y="238" T="201656297" />
  <Point X="104" Y="243" T="201656306" />
  <Point X="104" Y="245" T="201656314" />
  <Point X="105" Y="248" T="201656323" />
  <Point X="105" Y="251" T="201656332" />
  <Point X="105" Y="253" T="201656341" />
  <Point X="106" Y="251" T="201656386" />
  <Point X="106" Y="249" T="201656395" />
  <Point X="106" Y="245" T="201656405" />
  <Point X="107" Y="243" T="201656406" />
  <Point X="107" Y="241" T="201656416" />
  <Point X="111" Y="232" T="201656427" />
  <Point X="117" Y="221" T="201656438" />
  <Point X="122" Y="213" T="201656449" />
  <Point X="132" Y="199" T="201656460" />
  <Point X="144" Y="185" T="201656472" />
  <Point X="155" Y="173" T="201656483" />
  <Point X="163" Y="165" T="201656495" />
  <Point X="168" Y="161" T="201656507" />
  <Point X="167" Y="164" T="201656561" />
  <Point X="165" Y="165" T="201656579" />
</Gesture>