<?xml version="1.0" encoding="utf-8" standalone="yes"?>
<Gesture Name="delete_mark05" Subject="2" Speed="medium" Number="5" NumPts="61" Millseconds="840" AppName="Gestures" AppVer="3.5.0.0" Date="Monday, March 05, 2007" TimeOfDay="8:53:52 PM">
  <Point X="107" Y="154" T="10321539" />
  <Point X="110" Y="155" T="10321564" />
  <Point X="112" Y="157" T="10321575" />
  <Point X="115" Y="161" T="10321588" />
  <Point X="117" Y="163" T="10321596" />
  <Point X="119" Y="165" T="10321604" />
  <Point X="122" Y="169" T="10321612" />
  <Point X="123" Y="171" T="10321619" />
  <Point X="126" Y="175" T="10321626" />
  <Point X="130" Y="178" T="10321633" />
  <Point X="133" Y="182" T="10321640" />
  <Point X="137" Y="186" T="10321648" />
  <Point X="140" Y="191" T="10321656" />
  <Point X="144" Y="195" T="10321664" />
  <Point X="148" Y="199" T="10321673" />
  <Point X="149" Y="202" T="10321681" />
  <Point X="154" Y="208" T="10321690" />
  <Point X="157" Y="212" T="10321699" />
  <Point X="159" Y="216" T="10321708" />
  <Point X="162" Y="219" T="10321717" />
  <Point X="165" Y="224" T="10321727" />
  <Point X="166" Y="226" T="10321736" />
  <Point X="167" Y="229" T="10321737" />
  <Point X="168" Y="231" T="10321747" />
  <Point X="169" Y="233" T="10321757" />
  <Point X="170" Y="235" T="10321768" />
  <Point X="170" Y="237" T="10321780" />
  <Point X="168" Y="238" T="10321836" />
  <Point X="165" Y="237" T="10321848" />
  <Point X="163" Y="237" T="10321859" />
  <Point X="160" Y="237" T="10321870" />
  <Point X="154" Y="235" T="10321881" />
  <Point X="147" Y="235" T="10321893" />
  <Point X="141" Y="235" T="10321905" />
  <Point X="133" Y="235" T="10321918" />
  <Point X="126" Y="238" T="10321930" />
  <Point X="119" Y="239" T="10321943" />
  <Point X="115" Y="240" T="10321956" />
  <Point X="112" Y="241" T="10321957" />
  <Point X="107" Y="242" T="10321970" />
  <Point X="105" Y="242" T="10321984" />
  <Point X="103" Y="243" T="10321997" />
  <Point X="100" Y="244" T="10322011" />
  <Point X="98" Y="245" T="10322025" />
  <Point X="96" Y="246" T="10322039" />
  <Point X="94" Y="246" T="10322054" />
  <Point X="93" Y="243" T="10322145" />
  <Point X="95" Y="241" T="10322164" />
  <Point X="97" Y="239" T="10322179" />
  <Point X="101" Y="234" T="10322194" />
  <Point X="105" Y="230" T="10322210" />
  <Point X="114" Y="219" T="10322226" />
  <Point X="122" Y="207" T="10322243" />
  <Point X="130" Y="196" T="10322259" />
  <Point X="138" Y="185" T="10322276" />
  <Point X="144" Y="177" T="10322293" />
  <Point X="151" Y="169" T="10322310" />
  <Point X="155" Y="162" T="10322327" />
  <Point X="158" Y="157" T="10322344" />
  <Point X="160" Y="155" T="10322361" />
  <Point X="162" Y="152" T="10322379" />
</Gesture>