<?xml version="1.0" encoding="utf-8" standalone="yes"?>
<Gesture Name="star03" Subject="10" Speed="fast" Number="3" NumPts="68" Millseconds="749" AppName="Gestures" AppVer="3.7.0.0" Date="Wednesday, March 14, 2007" TimeOfDay="11:42:41 AM">
  <Point X="60" Y="257" T="252550420" />
  <Point X="60" Y="255" T="252550436" />
  <Point X="62" Y="252" T="252550445" />
  <Point X="63" Y="250" T="252550452" />
  <Point X="64" Y="247" T="252550457" />
  <Point X="65" Y="245" T="252550463" />
  <Point X="66" Y="242" T="252550464" />
  <Point X="67" Y="240" T="252550471" />
  <Point X="70" Y="235" T="252550477" />
  <Point X="71" Y="231" T="252550484" />
  <Point X="72" Y="228" T="252550485" />
  <Point X="74" Y="225" T="252550491" />
  <Point X="75" Y="222" T="252550493" />
  <Point X="77" Y="212" T="252550500" />
  <Point X="79" Y="208" T="252550508" />
  <Point X="80" Y="203" T="252550509" />
  <Point X="83" Y="193" T="252550517" />
  <Point X="85" Y="184" T="252550526" />
  <Point X="88" Y="174" T="252550534" />
  <Point X="91" Y="166" T="252550543" />
  <Point X="92" Y="163" T="252550544" />
  <Point X="95" Y="159" T="252550554" />
  <Point X="97" Y="156" T="252550563" />
  <Point X="99" Y="154" T="252550573" />
  <Point X="102" Y="154" T="252550583" />
  <Point X="110" Y="164" T="252550593" />
  <Point X="116" Y="172" T="252550603" />
  <Point X="118" Y="178" T="252550604" />
  <Point X="123" Y="191" T="252550615" />
  <Point X="125" Y="198" T="252550616" />
  <Point X="130" Y="210" T="252550627" />
  <Point X="132" Y="216" T="252550628" />
  <Point X="136" Y="234" T="252550640" />
  <Point X="139" Y="251" T="252550653" />
  <Point X="141" Y="261" T="252550665" />
  <Point X="143" Y="268" T="252550677" />
  <Point X="143" Y="270" T="252550689" />
  <Point X="143" Y="272" T="252550702" />
  <Point X="140" Y="270" T="252550714" />
  <Point X="135" Y="266" T="252550728" />
  <Point X="133" Y="264" T="252550729" />
  <Point X="124" Y="256" T="252550743" />
  <Point X="107" Y="245" T="252550757" />
  <Point X="93" Y="235" T="252550771" />
  <Point X="88" Y="232" T="252550772" />
  <Point X="74" Y="224" T="252550787" />
  <Point X="57" Y="213" T="252550803" />
  <Point X="44" Y="203" T="252550818" />
  <Point X="36" Y="196" T="252550833" />
  <Point X="35" Y="193" T="252550848" />
  <Point X="37" Y="191" T="252550864" />
  <Point X="47" Y="192" T="252550880" />
  <Point X="67" Y="197" T="252550897" />
  <Point X="91" Y="202" T="252550914" />
  <Point X="115" Y="206" T="252550932" />
  <Point X="120" Y="206" T="252550933" />
  <Point X="140" Y="207" T="252550950" />
  <Point X="159" Y="206" T="252550971" />
  <Point X="170" Y="205" T="252550989" />
  <Point X="172" Y="205" T="252551007" />
  <Point X="170" Y="205" T="252551024" />
  <Point X="150" Y="210" T="252551049" />
  <Point X="111" Y="224" T="252551076" />
  <Point X="78" Y="243" T="252551101" />
  <Point X="55" Y="261" T="252551128" />
  <Point X="52" Y="263" T="252551129" />
  <Point X="44" Y="268" T="252551149" />
  <Point X="42" Y="270" T="252551169" />
</Gesture>