<?xml version="1.0" encoding="utf-8" standalone="yes"?>
<Gesture Name="asterisk~03" Subject="99" InputType="finger" Speed="SLOW" NumPts="126">
	<Stroke index="1">
		<Point X="116" Y="3" T="1302294591016" Pressure="128" />
		<Point X="114" Y="46" T="1302294591016" Pressure="128" />
		<Point X="114" Y="49" T="1302294591032" Pressure="128" />
		<Point X="114" Y="53" T="1302294591048" Pressure="128" />
		<Point X="114" Y="56" T="1302294591048" Pressure="128" />
		<Point X="113" Y="60" T="1302294591063" Pressure="128" />
		<Point X="114" Y="63" T="1302294591079" Pressure="128" />
		<Point X="113" Y="66" T="1302294591094" Pressure="128" />
		<Point X="113" Y="70" T="1302294591094" Pressure="128" />
		<Point X="113" Y="73" T="1302294591110" Pressure="128" />
		<Point X="112" Y="78" T="1302294591126" Pressure="128" />
		<Point X="112" Y="80" T="1302294591126" Pressure="128" />
		<Point X="112" Y="83" T="1302294591141" Pressure="128" />
		<Point X="112" Y="88" T="1302294591157" Pressure="128" />
		<Point X="112" Y="90" T="1302294591172" Pressure="128" />
		<Point X="112" Y="94" T="1302294591172" Pressure="128" />
		<Point X="112" Y="98" T="1302294591188" Pressure="128" />
		<Point X="111" Y="100" T="1302294591204" Pressure="128" />
		<Point X="111" Y="103" T="1302294591204" Pressure="128" />
		<Point X="111" Y="106" T="1302294591219" Pressure="128" />
		<Point X="111" Y="108" T="1302294591235" Pressure="128" />
		<Point X="111" Y="111" T="1302294591235" Pressure="128" />
		<Point X="111" Y="113" T="1302294591250" Pressure="128" />
		<Point X="111" Y="115" T="1302294591266" Pressure="128" />
		<Point X="111" Y="118" T="1302294591282" Pressure="128" />
		<Point X="111" Y="119" T="1302294591282" Pressure="128" />
		<Point X="111" Y="121" T="1302294591297" Pressure="128" />
		<Point X="111" Y="123" T="1302294591313" Pressure="128" />
		<Point X="110" Y="123" T="1302294591313" Pressure="128" />
		<Point X="110" Y="126" T="1302294591344" Pressure="128" />
		<Point X="110" Y="128" T="1302294591360" Pressure="128" />
		<Point X="110" Y="130" T="1302294591391" Pressure="128" />
		<Point X="110" Y="131" T="1302294591406" Pressure="128" />
		<Point X="110" Y="131" T="1302294591438" Pressure="128" />
	</Stroke>
	<Stroke index="2">
		<Point X="29" Y="19" T="1302294592108" Pressure="128" />
		<Point X="77" Y="48" T="1302294592108" Pressure="128" />
		<Point X="80" Y="50" T="1302294592124" Pressure="128" />
		<Point X="85" Y="53" T="1302294592140" Pressure="128" />
		<Point X="87" Y="54" T="1302294592140" Pressure="128" />
		<Point X="91" Y="55" T="1302294592155" Pressure="128" />
		<Point X="94" Y="58" T="1302294592171" Pressure="128" />
		<Point X="97" Y="59" T="1302294592171" Pressure="128" />
		<Point X="100" Y="60" T="1302294592186" Pressure="128" />
		<Point X="103" Y="63" T="1302294592202" Pressure="128" />
		<Point X="106" Y="63" T="1302294592218" Pressure="128" />
		<Point X="110" Y="65" T="1302294592218" Pressure="128" />
		<Point X="112" Y="68" T="1302294592233" Pressure="128" />
		<Point X="115" Y="68" T="1302294592249" Pressure="128" />
		<Point X="117" Y="69" T="1302294592249" Pressure="128" />
		<Point X="120" Y="70" T="1302294592264" Pressure="128" />
		<Point X="122" Y="73" T="1302294592280" Pressure="128" />
		<Point X="124" Y="73" T="1302294592281" Pressure="128" />
		<Point X="126" Y="74" T="1302294592296" Pressure="128" />
		<Point X="128" Y="75" T="1302294592311" Pressure="128" />
		<Point X="130" Y="75" T="1302294592327" Pressure="128" />
		<Point X="132" Y="78" T="1302294592327" Pressure="128" />
		<Point X="135" Y="78" T="1302294592342" Pressure="128" />
		<Point X="135" Y="79" T="1302294592358" Pressure="128" />
		<Point X="138" Y="80" T="1302294592359" Pressure="128" />
		<Point X="139" Y="81" T="1302294592374" Pressure="128" />
		<Point X="142" Y="83" T="1302294592389" Pressure="128" />
		<Point X="144" Y="84" T="1302294592405" Pressure="128" />
		<Point X="147" Y="86" T="1302294592405" Pressure="128" />
		<Point X="149" Y="88" T="1302294592420" Pressure="128" />
		<Point X="151" Y="89" T="1302294592436" Pressure="128" />
		<Point X="153" Y="91" T="1302294592436" Pressure="128" />
		<Point X="155" Y="93" T="1302294592452" Pressure="128" />
		<Point X="158" Y="93" T="1302294592467" Pressure="128" />
		<Point X="160" Y="95" T="1302294592483" Pressure="128" />
		<Point X="163" Y="96" T="1302294592483" Pressure="128" />
		<Point X="165" Y="98" T="1302294592498" Pressure="128" />
		<Point X="167" Y="99" T="1302294592514" Pressure="128" />
		<Point X="169" Y="100" T="1302294592514" Pressure="128" />
		<Point X="171" Y="101" T="1302294592530" Pressure="128" />
		<Point X="173" Y="103" T="1302294592545" Pressure="128" />
		<Point X="174" Y="103" T="1302294592561" Pressure="128" />
		<Point X="176" Y="104" T="1302294592561" Pressure="128" />
		<Point X="177" Y="105" T="1302294592576" Pressure="128" />
		<Point X="178" Y="105" T="1302294592592" Pressure="128" />
		<Point X="178" Y="105" T="1302294592608" Pressure="128" />
	</Stroke>
	<Stroke index="3">
		<Point X="165" Y="20" T="1302294593169" Pressure="128" />
		<Point X="131" Y="40" T="1302294593169" Pressure="128" />
		<Point X="129" Y="43" T="1302294593185" Pressure="128" />
		<Point X="127" Y="44" T="1302294593185" Pressure="128" />
		<Point X="125" Y="48" T="1302294593200" Pressure="128" />
		<Point X="123" Y="48" T="1302294593216" Pressure="128" />
		<Point X="121" Y="51" T="1302294593216" Pressure="128" />
		<Point X="119" Y="53" T="1302294593232" Pressure="128" />
		<Point X="117" Y="55" T="1302294593247" Pressure="128" />
		<Point X="115" Y="58" T="1302294593263" Pressure="128" />
		<Point X="113" Y="59" T="1302294593263" Pressure="128" />
		<Point X="111" Y="60" T="1302294593278" Pressure="128" />
		<Point X="110" Y="63" T="1302294593294" Pressure="128" />
		<Point X="107" Y="63" T="1302294593294" Pressure="128" />
		<Point X="105" Y="65" T="1302294593310" Pressure="128" />
		<Point X="103" Y="68" T="1302294593325" Pressure="128" />
		<Point X="100" Y="69" T="1302294593341" Pressure="128" />
		<Point X="99" Y="70" T="1302294593341" Pressure="128" />
		<Point X="97" Y="73" T="1302294593356" Pressure="128" />
		<Point X="95" Y="73" T="1302294593372" Pressure="128" />
		<Point X="93" Y="75" T="1302294593372" Pressure="128" />
		<Point X="90" Y="76" T="1302294593388" Pressure="128" />
		<Point X="89" Y="78" T="1302294593403" Pressure="128" />
		<Point X="86" Y="79" T="1302294593403" Pressure="128" />
		<Point X="85" Y="80" T="1302294593419" Pressure="128" />
		<Point X="83" Y="81" T="1302294593434" Pressure="128" />
		<Point X="81" Y="83" T="1302294593450" Pressure="128" />
		<Point X="79" Y="84" T="1302294593450" Pressure="128" />
		<Point X="77" Y="85" T="1302294593466" Pressure="128" />
		<Point X="75" Y="88" T="1302294593481" Pressure="128" />
		<Point X="74" Y="88" T="1302294593481" Pressure="128" />
		<Point X="72" Y="89" T="1302294593497" Pressure="128" />
		<Point X="70" Y="91" T="1302294593512" Pressure="128" />
		<Point X="68" Y="93" T="1302294593528" Pressure="128" />
		<Point X="66" Y="93" T="1302294593528" Pressure="128" />
		<Point X="65" Y="94" T="1302294593544" Pressure="128" />
		<Point X="63" Y="95" T="1302294593559" Pressure="128" />
		<Point X="61" Y="98" T="1302294593559" Pressure="128" />
		<Point X="60" Y="98" T="1302294593575" Pressure="128" />
		<Point X="58" Y="99" T="1302294593590" Pressure="128" />
		<Point X="56" Y="100" T="1302294593606" Pressure="128" />
		<Point X="54" Y="101" T="1302294593606" Pressure="128" />
		<Point X="52" Y="103" T="1302294593637" Pressure="128" />
		<Point X="51" Y="104" T="1302294593653" Pressure="128" />
		<Point X="49" Y="106" T="1302294593684" Pressure="128" />
		<Point X="49" Y="106" T="1302294593731" Pressure="128" />
	</Stroke>
</Gesture>
