<?xml version="1.0" encoding="utf-8" standalone="yes"?>
<Gesture Name="null~08" Subject="22" InputType="stylus" Speed="MEDIUM" NumPts="83">
	<Stroke index="1">
		<Point X="100" Y="38" T="1302288586966" Pressure="128" />
		<Point X="106" Y="33" T="1302288586966" Pressure="128" />
		<Point X="81" Y="40" T="1302288586966" Pressure="128" />
		<Point X="72" Y="46" T="1302288586966" Pressure="128" />
		<Point X="68" Y="50" T="1302288586981" Pressure="128" />
		<Point X="64" Y="55" T="1302288586981" Pressure="128" />
		<Point X="60" Y="59" T="1302288586997" Pressure="128" />
		<Point X="57" Y="65" T="1302288586997" Pressure="128" />
		<Point X="55" Y="70" T="1302288587013" Pressure="128" />
		<Point X="53" Y="76" T="1302288587013" Pressure="128" />
		<Point X="52" Y="81" T="1302288587013" Pressure="128" />
		<Point X="52" Y="87" T="1302288587028" Pressure="128" />
		<Point X="54" Y="92" T="1302288587044" Pressure="128" />
		<Point X="56" Y="97" T="1302288587044" Pressure="128" />
		<Point X="59" Y="102" T="1302288587044" Pressure="128" />
		<Point X="62" Y="106" T="1302288587059" Pressure="128" />
		<Point X="67" Y="109" T="1302288587059" Pressure="128" />
		<Point X="73" Y="112" T="1302288587075" Pressure="128" />
		<Point X="79" Y="115" T="1302288587076" Pressure="128" />
		<Point X="85" Y="116" T="1302288587091" Pressure="128" />
		<Point X="93" Y="117" T="1302288587091" Pressure="128" />
		<Point X="100" Y="118" T="1302288587106" Pressure="128" />
		<Point X="107" Y="118" T="1302288587122" Pressure="128" />
		<Point X="115" Y="117" T="1302288587122" Pressure="128" />
		<Point X="122" Y="116" T="1302288587122" Pressure="128" />
		<Point X="129" Y="114" T="1302288587122" Pressure="128" />
		<Point X="136" Y="113" T="1302288587137" Pressure="128" />
		<Point X="142" Y="110" T="1302288587137" Pressure="128" />
		<Point X="148" Y="108" T="1302288587153" Pressure="128" />
		<Point X="153" Y="106" T="1302288587153" Pressure="128" />
		<Point X="157" Y="103" T="1302288587169" Pressure="128" />
		<Point X="161" Y="100" T="1302288587169" Pressure="128" />
		<Point X="165" Y="96" T="1302288587184" Pressure="128" />
		<Point X="168" Y="93" T="1302288587184" Pressure="128" />
		<Point X="170" Y="88" T="1302288587184" Pressure="128" />
		<Point X="171" Y="84" T="1302288587200" Pressure="128" />
		<Point X="172" Y="79" T="1302288587215" Pressure="128" />
		<Point X="172" Y="74" T="1302288587215" Pressure="128" />
		<Point X="171" Y="69" T="1302288587215" Pressure="128" />
		<Point X="168" Y="64" T="1302288587231" Pressure="128" />
		<Point X="165" Y="59" T="1302288587231" Pressure="128" />
		<Point X="161" Y="55" T="1302288587247" Pressure="128" />
		<Point X="156" Y="51" T="1302288587262" Pressure="128" />
		<Point X="150" Y="48" T="1302288587262" Pressure="128" />
		<Point X="143" Y="45" T="1302288587262" Pressure="128" />
		<Point X="136" Y="43" T="1302288587278" Pressure="128" />
		<Point X="129" Y="40" T="1302288587293" Pressure="128" />
		<Point X="123" Y="38" T="1302288587293" Pressure="128" />
		<Point X="117" Y="37" T="1302288587309" Pressure="128" />
		<Point X="111" Y="36" T="1302288587310" Pressure="128" />
		<Point X="106" Y="35" T="1302288587325" Pressure="128" />
		<Point X="103" Y="35" T="1302288587325" Pressure="128" />
		<Point X="100" Y="35" T="1302288587340" Pressure="128" />
		<Point X="98" Y="37" T="1302288587340" Pressure="128" />
		<Point X="97" Y="38" T="1302288587356" Pressure="128" />
		<Point X="96" Y="40" T="1302288587356" Pressure="128" />
		<Point X="96" Y="43" T="1302288587371" Pressure="128" />
		<Point X="96" Y="43" T="1302288587371" Pressure="128" />
	</Stroke>
	<Stroke index="2">
		<Point X="154" Y="21" T="1302288587715" Pressure="128" />
		<Point X="156" Y="16" T="1302288587715" Pressure="128" />
		<Point X="134" Y="47" T="1302288587715" Pressure="128" />
		<Point X="125" Y="61" T="1302288587715" Pressure="128" />
		<Point X="121" Y="69" T="1302288587730" Pressure="128" />
		<Point X="116" Y="77" T="1302288587746" Pressure="128" />
		<Point X="111" Y="84" T="1302288587746" Pressure="128" />
		<Point X="107" Y="92" T="1302288587746" Pressure="128" />
		<Point X="102" Y="99" T="1302288587761" Pressure="128" />
		<Point X="97" Y="106" T="1302288587761" Pressure="128" />
		<Point X="92" Y="112" T="1302288587777" Pressure="128" />
		<Point X="87" Y="117" T="1302288587777" Pressure="128" />
		<Point X="83" Y="122" T="1302288587793" Pressure="128" />
		<Point X="80" Y="127" T="1302288587793" Pressure="128" />
		<Point X="77" Y="130" T="1302288587808" Pressure="128" />
		<Point X="75" Y="133" T="1302288587808" Pressure="128" />
		<Point X="74" Y="135" T="1302288587824" Pressure="128" />
		<Point X="73" Y="136" T="1302288587824" Pressure="128" />
		<Point X="73" Y="137" T="1302288587839" Pressure="128" />
		<Point X="73" Y="138" T="1302288587839" Pressure="128" />
		<Point X="74" Y="137" T="1302288587855" Pressure="128" />
		<Point X="75" Y="137" T="1302288587855" Pressure="128" />
		<Point X="75" Y="136" T="1302288587856" Pressure="128" />
		<Point X="76" Y="134" T="1302288587871" Pressure="128" />
		<Point X="76" Y="134" T="1302288587871" Pressure="128" />
	</Stroke>
</Gesture>
