<?xml version="1.0" encoding="utf-8" standalone="yes"?>
<Gesture Name="five_point_star~05" Subject="22" InputType="stylus" Speed="SLOW" NumPts="237">
	<Stroke index="1">
		<Point X="53" Y="42" T="1302287723598" Pressure="128" />
		<Point X="52" Y="38" T="1302287723598" Pressure="128" />
		<Point X="68" Y="57" T="1302287723598" Pressure="128" />
		<Point X="74" Y="63" T="1302287723598" Pressure="128" />
		<Point X="77" Y="67" T="1302287723598" Pressure="128" />
		<Point X="80" Y="70" T="1302287723614" Pressure="128" />
		<Point X="83" Y="74" T="1302287723629" Pressure="128" />
		<Point X="86" Y="78" T="1302287723629" Pressure="128" />
		<Point X="89" Y="81" T="1302287723629" Pressure="128" />
		<Point X="92" Y="85" T="1302287723645" Pressure="128" />
		<Point X="95" Y="88" T="1302287723660" Pressure="128" />
		<Point X="97" Y="92" T="1302287723660" Pressure="128" />
		<Point X="100" Y="95" T="1302287723660" Pressure="128" />
		<Point X="103" Y="99" T="1302287723676" Pressure="128" />
		<Point X="105" Y="102" T="1302287723676" Pressure="128" />
		<Point X="108" Y="105" T="1302287723692" Pressure="128" />
		<Point X="110" Y="108" T="1302287723691" Pressure="128" />
		<Point X="113" Y="110" T="1302287723707" Pressure="128" />
		<Point X="116" Y="113" T="1302287723707" Pressure="128" />
		<Point X="118" Y="116" T="1302287723723" Pressure="128" />
		<Point X="120" Y="118" T="1302287723723" Pressure="128" />
		<Point X="122" Y="120" T="1302287723738" Pressure="128" />
		<Point X="124" Y="123" T="1302287723738" Pressure="128" />
		<Point X="126" Y="125" T="1302287723754" Pressure="128" />
		<Point X="128" Y="127" T="1302287723754" Pressure="128" />
		<Point X="130" Y="129" T="1302287723770" Pressure="128" />
		<Point X="132" Y="131" T="1302287723770" Pressure="128" />
		<Point X="133" Y="133" T="1302287723785" Pressure="128" />
		<Point X="135" Y="135" T="1302287723785" Pressure="128" />
		<Point X="136" Y="136" T="1302287723801" Pressure="128" />
		<Point X="138" Y="138" T="1302287723801" Pressure="128" />
		<Point X="139" Y="139" T="1302287723816" Pressure="128" />
		<Point X="140" Y="140" T="1302287723816" Pressure="128" />
		<Point X="141" Y="141" T="1302287723832" Pressure="128" />
		<Point X="141" Y="142" T="1302287723832" Pressure="128" />
		<Point X="142" Y="143" T="1302287723848" Pressure="128" />
		<Point X="143" Y="144" T="1302287723848" Pressure="128" />
		<Point X="143" Y="145" T="1302287723863" Pressure="128" />
		<Point X="143" Y="146" T="1302287723863" Pressure="128" />
		<Point X="144" Y="147" T="1302287723879" Pressure="128" />
		<Point X="143" Y="146" T="1302287723957" Pressure="128" />
		<Point X="143" Y="145" T="1302287723972" Pressure="128" />
		<Point X="142" Y="143" T="1302287723972" Pressure="128" />
		<Point X="142" Y="141" T="1302287723988" Pressure="128" />
		<Point X="142" Y="139" T="1302287723988" Pressure="128" />
		<Point X="141" Y="136" T="1302287724004" Pressure="128" />
		<Point X="141" Y="133" T="1302287724004" Pressure="128" />
		<Point X="141" Y="130" T="1302287724019" Pressure="128" />
		<Point X="141" Y="127" T="1302287724019" Pressure="128" />
		<Point X="141" Y="124" T="1302287724019" Pressure="128" />
		<Point X="140" Y="122" T="1302287724035" Pressure="128" />
		<Point X="140" Y="119" T="1302287724050" Pressure="128" />
		<Point X="140" Y="117" T="1302287724050" Pressure="128" />
		<Point X="139" Y="114" T="1302287724050" Pressure="128" />
		<Point X="139" Y="112" T="1302287724066" Pressure="128" />
		<Point X="138" Y="110" T="1302287724082" Pressure="128" />
		<Point X="138" Y="107" T="1302287724082" Pressure="128" />
		<Point X="138" Y="105" T="1302287724097" Pressure="128" />
		<Point X="138" Y="102" T="1302287724097" Pressure="128" />
		<Point X="138" Y="99" T="1302287724097" Pressure="128" />
		<Point X="137" Y="96" T="1302287724113" Pressure="128" />
		<Point X="137" Y="93" T="1302287724128" Pressure="128" />
		<Point X="137" Y="91" T="1302287724128" Pressure="128" />
		<Point X="137" Y="88" T="1302287724128" Pressure="128" />
		<Point X="137" Y="86" T="1302287724144" Pressure="128" />
		<Point X="137" Y="83" T="1302287724144" Pressure="128" />
		<Point X="136" Y="81" T="1302287724160" Pressure="128" />
		<Point X="136" Y="80" T="1302287724160" Pressure="128" />
		<Point X="135" Y="77" T="1302287724175" Pressure="128" />
		<Point X="135" Y="75" T="1302287724175" Pressure="128" />
		<Point X="134" Y="73" T="1302287724191" Pressure="128" />
		<Point X="134" Y="70" T="1302287724191" Pressure="128" />
		<Point X="133" Y="66" T="1302287724206" Pressure="128" />
		<Point X="133" Y="63" T="1302287724206" Pressure="128" />
		<Point X="132" Y="59" T="1302287724222" Pressure="128" />
		<Point X="132" Y="56" T="1302287724222" Pressure="128" />
		<Point X="132" Y="52" T="1302287724238" Pressure="128" />
		<Point X="131" Y="49" T="1302287724238" Pressure="128" />
		<Point X="131" Y="46" T="1302287724253" Pressure="128" />
		<Point X="130" Y="44" T="1302287724253" Pressure="128" />
		<Point X="130" Y="42" T="1302287724253" Pressure="128" />
		<Point X="129" Y="40" T="1302287724269" Pressure="128" />
		<Point X="129" Y="38" T="1302287724284" Pressure="128" />
		<Point X="128" Y="37" T="1302287724284" Pressure="128" />
		<Point X="127" Y="34" T="1302287724284" Pressure="128" />
		<Point X="127" Y="32" T="1302287724300" Pressure="128" />
		<Point X="126" Y="30" T="1302287724300" Pressure="128" />
		<Point X="126" Y="28" T="1302287724316" Pressure="128" />
		<Point X="126" Y="26" T="1302287724316" Pressure="128" />
		<Point X="125" Y="24" T="1302287724331" Pressure="128" />
		<Point X="125" Y="22" T="1302287724331" Pressure="128" />
		<Point X="125" Y="20" T="1302287724347" Pressure="128" />
		<Point X="124" Y="19" T="1302287724347" Pressure="128" />
		<Point X="124" Y="18" T="1302287724362" Pressure="128" />
		<Point X="124" Y="17" T="1302287724362" Pressure="128" />
		<Point X="124" Y="15" T="1302287724378" Pressure="128" />
		<Point X="124" Y="14" T="1302287724378" Pressure="128" />
		<Point X="123" Y="12" T="1302287724394" Pressure="128" />
		<Point X="123" Y="11" T="1302287724394" Pressure="128" />
		<Point X="123" Y="10" T="1302287724409" Pressure="128" />
		<Point X="123" Y="9" T="1302287724409" Pressure="128" />
		<Point X="123" Y="8" T="1302287724425" Pressure="128" />
		<Point X="123" Y="7" T="1302287724425" Pressure="128" />
		<Point X="123" Y="6" T="1302287724440" Pressure="128" />
		<Point X="122" Y="6" T="1302287724456" Pressure="128" />
		<Point X="122" Y="5" T="1302287724518" Pressure="128" />
		<Point X="121" Y="6" T="1302287724534" Pressure="128" />
		<Point X="120" Y="8" T="1302287724550" Pressure="128" />
		<Point X="119" Y="9" T="1302287724550" Pressure="128" />
		<Point X="118" Y="11" T="1302287724565" Pressure="128" />
		<Point X="116" Y="13" T="1302287724565" Pressure="128" />
		<Point X="115" Y="16" T="1302287724581" Pressure="128" />
		<Point X="113" Y="19" T="1302287724596" Pressure="128" />
		<Point X="111" Y="23" T="1302287724596" Pressure="128" />
		<Point X="109" Y="27" T="1302287724596" Pressure="128" />
		<Point X="106" Y="31" T="1302287724612" Pressure="128" />
		<Point X="104" Y="35" T="1302287724612" Pressure="128" />
		<Point X="101" Y="40" T="1302287724628" Pressure="128" />
		<Point X="98" Y="45" T="1302287724628" Pressure="128" />
		<Point X="96" Y="50" T="1302287724643" Pressure="128" />
		<Point X="92" Y="55" T="1302287724643" Pressure="128" />
		<Point X="89" Y="61" T="1302287724643" Pressure="128" />
		<Point X="86" Y="66" T="1302287724659" Pressure="128" />
		<Point X="83" Y="71" T="1302287724674" Pressure="128" />
		<Point X="80" Y="76" T="1302287724674" Pressure="128" />
		<Point X="77" Y="81" T="1302287724674" Pressure="128" />
		<Point X="74" Y="86" T="1302287724690" Pressure="128" />
		<Point X="71" Y="91" T="1302287724706" Pressure="128" />
		<Point X="69" Y="95" T="1302287724706" Pressure="128" />
		<Point X="66" Y="99" T="1302287724706" Pressure="128" />
		<Point X="65" Y="103" T="1302287724721" Pressure="128" />
		<Point X="63" Y="107" T="1302287724721" Pressure="128" />
		<Point X="62" Y="110" T="1302287724737" Pressure="128" />
		<Point X="60" Y="114" T="1302287724752" Pressure="128" />
		<Point X="59" Y="117" T="1302287724752" Pressure="128" />
		<Point X="57" Y="121" T="1302287724752" Pressure="128" />
		<Point X="56" Y="124" T="1302287724768" Pressure="128" />
		<Point X="55" Y="127" T="1302287724768" Pressure="128" />
		<Point X="53" Y="130" T="1302287724768" Pressure="128" />
		<Point X="52" Y="132" T="1302287724784" Pressure="128" />
		<Point X="50" Y="134" T="1302287724799" Pressure="128" />
		<Point X="49" Y="136" T="1302287724799" Pressure="128" />
		<Point X="48" Y="138" T="1302287724815" Pressure="128" />
		<Point X="47" Y="139" T="1302287724815" Pressure="128" />
		<Point X="47" Y="140" T="1302287724815" Pressure="128" />
		<Point X="46" Y="141" T="1302287724830" Pressure="128" />
		<Point X="47" Y="141" T="1302287724862" Pressure="128" />
		<Point X="47" Y="140" T="1302287724877" Pressure="128" />
		<Point X="49" Y="139" T="1302287724893" Pressure="128" />
		<Point X="50" Y="138" T="1302287724893" Pressure="128" />
		<Point X="52" Y="136" T="1302287724908" Pressure="128" />
		<Point X="54" Y="135" T="1302287724908" Pressure="128" />
		<Point X="57" Y="132" T="1302287724908" Pressure="128" />
		<Point X="60" Y="130" T="1302287724924" Pressure="128" />
		<Point X="62" Y="128" T="1302287724924" Pressure="128" />
		<Point X="66" Y="125" T="1302287724940" Pressure="128" />
		<Point X="69" Y="123" T="1302287724940" Pressure="128" />
		<Point X="73" Y="120" T="1302287724955" Pressure="128" />
		<Point X="77" Y="118" T="1302287724955" Pressure="128" />
		<Point X="81" Y="116" T="1302287724971" Pressure="128" />
		<Point X="85" Y="113" T="1302287724971" Pressure="128" />
		<Point X="89" Y="111" T="1302287724986" Pressure="128" />
		<Point X="94" Y="109" T="1302287724986" Pressure="128" />
		<Point X="98" Y="106" T="1302287725002" Pressure="128" />
		<Point X="103" Y="103" T="1302287725002" Pressure="128" />
		<Point X="108" Y="101" T="1302287725018" Pressure="128" />
		<Point X="113" Y="98" T="1302287725018" Pressure="128" />
		<Point X="117" Y="95" T="1302287725033" Pressure="128" />
		<Point X="122" Y="92" T="1302287725033" Pressure="128" />
		<Point X="127" Y="89" T="1302287725049" Pressure="128" />
		<Point X="132" Y="86" T="1302287725049" Pressure="128" />
		<Point X="136" Y="83" T="1302287725064" Pressure="128" />
		<Point X="140" Y="80" T="1302287725064" Pressure="128" />
		<Point X="145" Y="78" T="1302287725064" Pressure="128" />
		<Point X="148" Y="75" T="1302287725080" Pressure="128" />
		<Point X="152" Y="72" T="1302287725096" Pressure="128" />
		<Point X="156" Y="70" T="1302287725096" Pressure="128" />
		<Point X="159" Y="67" T="1302287725096" Pressure="128" />
		<Point X="162" Y="65" T="1302287725111" Pressure="128" />
		<Point X="165" Y="63" T="1302287725127" Pressure="128" />
		<Point X="168" Y="61" T="1302287725127" Pressure="128" />
		<Point X="171" Y="59" T="1302287725142" Pressure="128" />
		<Point X="173" Y="58" T="1302287725142" Pressure="128" />
		<Point X="174" Y="57" T="1302287725142" Pressure="128" />
		<Point X="176" Y="56" T="1302287725158" Pressure="128" />
		<Point X="177" Y="55" T="1302287725174" Pressure="128" />
		<Point X="178" Y="55" T="1302287725174" Pressure="128" />
		<Point X="178" Y="54" T="1302287725189" Pressure="128" />
		<Point X="177" Y="54" T="1302287725236" Pressure="128" />
		<Point X="176" Y="54" T="1302287725252" Pressure="128" />
		<Point X="175" Y="55" T="1302287725252" Pressure="128" />
		<Point X="174" Y="55" T="1302287725267" Pressure="128" />
		<Point X="173" Y="55" T="1302287725267" Pressure="128" />
		<Point X="171" Y="56" T="1302287725283" Pressure="128" />
		<Point X="169" Y="56" T="1302287725283" Pressure="128" />
		<Point X="167" Y="56" T="1302287725298" Pressure="128" />
		<Point X="165" Y="57" T="1302287725298" Pressure="128" />
		<Point X="163" Y="57" T="1302287725298" Pressure="128" />
		<Point X="160" Y="57" T="1302287725314" Pressure="128" />
		<Point X="158" Y="58" T="1302287725330" Pressure="128" />
		<Point X="155" Y="58" T="1302287725330" Pressure="128" />
		<Point X="152" Y="58" T="1302287725330" Pressure="128" />
		<Point X="149" Y="58" T="1302287725345" Pressure="128" />
		<Point X="146" Y="58" T="1302287725345" Pressure="128" />
		<Point X="143" Y="58" T="1302287725361" Pressure="128" />
		<Point X="139" Y="57" T="1302287725361" Pressure="128" />
		<Point X="136" Y="57" T="1302287725376" Pressure="128" />
		<Point X="132" Y="57" T="1302287725376" Pressure="128" />
		<Point X="129" Y="57" T="1302287725392" Pressure="128" />
		<Point X="125" Y="56" T="1302287725392" Pressure="128" />
		<Point X="122" Y="56" T="1302287725408" Pressure="128" />
		<Point X="118" Y="56" T="1302287725408" Pressure="128" />
		<Point X="114" Y="55" T="1302287725423" Pressure="128" />
		<Point X="111" Y="55" T="1302287725423" Pressure="128" />
		<Point X="107" Y="55" T="1302287725439" Pressure="128" />
		<Point X="104" Y="55" T="1302287725439" Pressure="128" />
		<Point X="100" Y="55" T="1302287725454" Pressure="128" />
		<Point X="97" Y="54" T="1302287725454" Pressure="128" />
		<Point X="94" Y="54" T="1302287725470" Pressure="128" />
		<Point X="91" Y="53" T="1302287725470" Pressure="128" />
		<Point X="88" Y="53" T="1302287725470" Pressure="128" />
		<Point X="85" Y="52" T="1302287725486" Pressure="128" />
		<Point X="82" Y="51" T="1302287725486" Pressure="128" />
		<Point X="79" Y="50" T="1302287725501" Pressure="128" />
		<Point X="76" Y="50" T="1302287725501" Pressure="128" />
		<Point X="73" Y="49" T="1302287725517" Pressure="128" />
		<Point X="70" Y="49" T="1302287725517" Pressure="128" />
		<Point X="67" Y="49" T="1302287725517" Pressure="128" />
		<Point X="64" Y="49" T="1302287725532" Pressure="128" />
		<Point X="62" Y="49" T="1302287725532" Pressure="128" />
		<Point X="60" Y="49" T="1302287725548" Pressure="128" />
		<Point X="58" Y="49" T="1302287725548" Pressure="128" />
		<Point X="56" Y="49" T="1302287725564" Pressure="128" />
		<Point X="54" Y="49" T="1302287725579" Pressure="128" />
		<Point X="53" Y="49" T="1302287725595" Pressure="128" />
		<Point X="54" Y="48" T="1302287725610" Pressure="128" />
		<Point X="54" Y="48" T="1302287725657" Pressure="128" />
	</Stroke>
</Gesture>
