<?xml version="1.0" encoding="utf-8" standalone="yes"?>
<Gesture Name="null~10" Subject="73" InputType="finger" Speed="FAST" NumPts="136">
	<Stroke index="1">
		<Point X="88" Y="50" T="1302188175803" Pressure="128" />
		<Point X="61" Y="96" T="1302188175803" Pressure="128" />
		<Point X="61" Y="100" T="1302188175803" Pressure="128" />
		<Point X="61" Y="103" T="1302188175819" Pressure="128" />
		<Point X="61" Y="106" T="1302188175834" Pressure="128" />
		<Point X="62" Y="110" T="1302188175850" Pressure="128" />
		<Point X="62" Y="113" T="1302188175850" Pressure="128" />
		<Point X="64" Y="116" T="1302188175866" Pressure="128" />
		<Point X="66" Y="120" T="1302188175881" Pressure="128" />
		<Point X="67" Y="121" T="1302188175881" Pressure="128" />
		<Point X="69" Y="125" T="1302188175897" Pressure="128" />
		<Point X="72" Y="126" T="1302188175912" Pressure="128" />
		<Point X="75" Y="128" T="1302188175928" Pressure="128" />
		<Point X="77" Y="130" T="1302188175928" Pressure="128" />
		<Point X="80" Y="131" T="1302188175944" Pressure="128" />
		<Point X="83" Y="133" T="1302188175959" Pressure="128" />
		<Point X="87" Y="135" T="1302188175959" Pressure="128" />
		<Point X="90" Y="135" T="1302188175975" Pressure="128" />
		<Point X="94" Y="136" T="1302188175990" Pressure="128" />
		<Point X="98" Y="137" T="1302188176006" Pressure="128" />
		<Point X="102" Y="137" T="1302188176006" Pressure="128" />
		<Point X="106" Y="137" T="1302188176022" Pressure="128" />
		<Point X="111" Y="138" T="1302188176037" Pressure="128" />
		<Point X="115" Y="138" T="1302188176037" Pressure="128" />
		<Point X="119" Y="138" T="1302188176053" Pressure="128" />
		<Point X="123" Y="137" T="1302188176068" Pressure="128" />
		<Point X="127" Y="137" T="1302188176084" Pressure="128" />
		<Point X="131" Y="136" T="1302188176084" Pressure="128" />
		<Point X="135" Y="135" T="1302188176100" Pressure="128" />
		<Point X="139" Y="135" T="1302188176115" Pressure="128" />
		<Point X="143" Y="133" T="1302188176115" Pressure="128" />
		<Point X="146" Y="131" T="1302188176131" Pressure="128" />
		<Point X="150" Y="130" T="1302188176146" Pressure="128" />
		<Point X="153" Y="127" T="1302188176147" Pressure="128" />
		<Point X="156" Y="125" T="1302188176162" Pressure="128" />
		<Point X="160" Y="125" T="1302188176178" Pressure="128" />
		<Point X="163" Y="121" T="1302188176193" Pressure="128" />
		<Point X="165" Y="120" T="1302188176193" Pressure="128" />
		<Point X="167" Y="117" T="1302188176209" Pressure="128" />
		<Point X="169" Y="115" T="1302188176224" Pressure="128" />
		<Point X="171" Y="112" T="1302188176225" Pressure="128" />
		<Point X="173" Y="110" T="1302188176240" Pressure="128" />
		<Point X="175" Y="107" T="1302188176256" Pressure="128" />
		<Point X="176" Y="105" T="1302188176271" Pressure="128" />
		<Point X="177" Y="102" T="1302188176271" Pressure="128" />
		<Point X="178" Y="100" T="1302188176287" Pressure="128" />
		<Point X="178" Y="97" T="1302188176302" Pressure="128" />
		<Point X="178" Y="95" T="1302188176302" Pressure="128" />
		<Point X="178" Y="92" T="1302188176318" Pressure="128" />
		<Point X="178" Y="90" T="1302188176334" Pressure="128" />
		<Point X="178" Y="88" T="1302188176349" Pressure="128" />
		<Point X="177" Y="85" T="1302188176349" Pressure="128" />
		<Point X="177" Y="83" T="1302188176365" Pressure="128" />
		<Point X="177" Y="81" T="1302188176380" Pressure="128" />
		<Point X="176" Y="80" T="1302188176380" Pressure="128" />
		<Point X="175" Y="77" T="1302188176396" Pressure="128" />
		<Point X="173" Y="75" T="1302188176412" Pressure="128" />
		<Point X="172" Y="73" T="1302188176427" Pressure="128" />
		<Point X="171" Y="71" T="1302188176427" Pressure="128" />
		<Point X="169" Y="70" T="1302188176443" Pressure="128" />
		<Point X="168" Y="67" T="1302188176458" Pressure="128" />
		<Point X="166" Y="65" T="1302188176458" Pressure="128" />
		<Point X="165" Y="63" T="1302188176474" Pressure="128" />
		<Point X="164" Y="61" T="1302188176490" Pressure="128" />
		<Point X="162" Y="60" T="1302188176505" Pressure="128" />
		<Point X="161" Y="58" T="1302188176505" Pressure="128" />
		<Point X="159" Y="56" T="1302188176521" Pressure="128" />
		<Point X="158" Y="55" T="1302188176536" Pressure="128" />
		<Point X="157" Y="53" T="1302188176536" Pressure="128" />
		<Point X="155" Y="52" T="1302188176552" Pressure="128" />
		<Point X="154" Y="51" T="1302188176568" Pressure="128" />
		<Point X="152" Y="50" T="1302188176583" Pressure="128" />
		<Point X="151" Y="50" T="1302188176583" Pressure="128" />
		<Point X="150" Y="48" T="1302188176599" Pressure="128" />
		<Point X="147" Y="46" T="1302188176614" Pressure="128" />
		<Point X="146" Y="45" T="1302188176614" Pressure="128" />
		<Point X="144" Y="45" T="1302188176630" Pressure="128" />
		<Point X="142" Y="45" T="1302188176646" Pressure="128" />
		<Point X="140" Y="43" T="1302188176661" Pressure="128" />
		<Point X="138" Y="42" T="1302188176661" Pressure="128" />
		<Point X="136" Y="41" T="1302188176677" Pressure="128" />
		<Point X="135" Y="40" T="1302188176692" Pressure="128" />
		<Point X="133" Y="40" T="1302188176692" Pressure="128" />
		<Point X="131" Y="40" T="1302188176708" Pressure="128" />
		<Point X="129" Y="38" T="1302188176724" Pressure="128" />
		<Point X="127" Y="37" T="1302188176739" Pressure="128" />
		<Point X="125" Y="37" T="1302188176739" Pressure="128" />
		<Point X="123" Y="37" T="1302188176755" Pressure="128" />
		<Point X="121" Y="37" T="1302188176770" Pressure="128" />
		<Point X="119" Y="36" T="1302188176770" Pressure="128" />
		<Point X="117" Y="36" T="1302188176786" Pressure="128" />
		<Point X="115" Y="36" T="1302188176802" Pressure="128" />
		<Point X="113" Y="36" T="1302188176817" Pressure="128" />
		<Point X="111" Y="36" T="1302188176817" Pressure="128" />
		<Point X="110" Y="37" T="1302188176833" Pressure="128" />
		<Point X="108" Y="37" T="1302188176848" Pressure="128" />
		<Point X="107" Y="37" T="1302188176864" Pressure="128" />
		<Point X="105" Y="37" T="1302188176911" Pressure="128" />
		<Point X="104" Y="38" T="1302188177270" Pressure="128" />
		<Point X="104" Y="38" T="1302188177924" Pressure="128" />
	</Stroke>
	<Stroke index="2">
		<Point X="13" Y="170" T="1302188178908" Pressure="128" />
		<Point X="67" Y="116" T="1302188178908" Pressure="128" />
		<Point X="73" Y="112" T="1302188178923" Pressure="128" />
		<Point X="78" Y="107" T="1302188178939" Pressure="128" />
		<Point X="84" Y="102" T="1302188178939" Pressure="128" />
		<Point X="90" Y="98" T="1302188178954" Pressure="128" />
		<Point X="96" Y="93" T="1302188178970" Pressure="128" />
		<Point X="101" Y="90" T="1302188178986" Pressure="128" />
		<Point X="107" Y="85" T="1302188178986" Pressure="128" />
		<Point X="112" Y="81" T="1302188179001" Pressure="128" />
		<Point X="118" Y="77" T="1302188179017" Pressure="128" />
		<Point X="123" Y="72" T="1302188179017" Pressure="128" />
		<Point X="129" Y="68" T="1302188179032" Pressure="128" />
		<Point X="134" Y="63" T="1302188179048" Pressure="128" />
		<Point X="139" Y="58" T="1302188179064" Pressure="128" />
		<Point X="145" Y="53" T="1302188179064" Pressure="128" />
		<Point X="151" Y="50" T="1302188179079" Pressure="128" />
		<Point X="157" Y="45" T="1302188179095" Pressure="128" />
		<Point X="162" Y="40" T="1302188179095" Pressure="128" />
		<Point X="168" Y="35" T="1302188179110" Pressure="128" />
		<Point X="175" Y="30" T="1302188179126" Pressure="128" />
		<Point X="181" Y="25" T="1302188179142" Pressure="128" />
		<Point X="187" Y="21" T="1302188179142" Pressure="128" />
		<Point X="192" Y="16" T="1302188179157" Pressure="128" />
		<Point X="198" Y="12" T="1302188179173" Pressure="128" />
		<Point X="204" Y="8" T="1302188179173" Pressure="128" />
		<Point X="208" Y="5" T="1302188179188" Pressure="128" />
		<Point X="212" Y="1" T="1302188179204" Pressure="128" />
		<Point X="216" Y="-2" T="1302188179220" Pressure="128" />
		<Point X="219" Y="-4" T="1302188179220" Pressure="128" />
		<Point X="222" Y="-5" T="1302188179235" Pressure="128" />
		<Point X="225" Y="-8" T="1302188179251" Pressure="128" />
		<Point X="226" Y="-9" T="1302188179251" Pressure="128" />
		<Point X="227" Y="-10" T="1302188179266" Pressure="128" />
		<Point X="228" Y="-10" T="1302188179298" Pressure="128" />
		<Point X="228" Y="-10" T="1302188179329" Pressure="128" />
	</Stroke>
</Gesture>
