<?xml version="1.0" encoding="utf-8" standalone="yes"?>
<Gesture Name="arrowhead~05" Subject="73" InputType="finger" Speed="FAST" NumPts="57">
	<Stroke index="1">
		<Point X="19" Y="93" T="1302187829030" Pressure="128" />
		<Point X="91" Y="100" T="1302187829046" Pressure="128" />
		<Point X="101" Y="100" T="1302187829046" Pressure="128" />
		<Point X="110" Y="101" T="1302187829061" Pressure="128" />
		<Point X="120" Y="101" T="1302187829077" Pressure="128" />
		<Point X="129" Y="101" T="1302187829077" Pressure="128" />
		<Point X="138" Y="102" T="1302187829093" Pressure="128" />
		<Point X="146" Y="102" T="1302187829108" Pressure="128" />
		<Point X="153" Y="103" T="1302187829108" Pressure="128" />
		<Point X="160" Y="103" T="1302187829124" Pressure="128" />
		<Point X="165" Y="105" T="1302187829139" Pressure="128" />
		<Point X="169" Y="105" T="1302187829155" Pressure="128" />
		<Point X="173" Y="105" T="1302187829155" Pressure="128" />
		<Point X="175" Y="105" T="1302187829171" Pressure="128" />
		<Point X="177" Y="105" T="1302187829186" Pressure="128" />
		<Point X="179" Y="105" T="1302187829186" Pressure="128" />
		<Point X="181" Y="105" T="1302187829217" Pressure="128" />
		<Point X="181" Y="105" T="1302187829342" Pressure="128" />
	</Stroke>
	<Stroke index="2">
		<Point X="151" Y="48" T="1302187830044" Pressure="128" />
		<Point X="201" Y="75" T="1302187830044" Pressure="128" />
		<Point X="206" Y="77" T="1302187830060" Pressure="128" />
		<Point X="211" Y="80" T="1302187830075" Pressure="128" />
		<Point X="215" Y="83" T="1302187830075" Pressure="128" />
		<Point X="219" Y="85" T="1302187830091" Pressure="128" />
		<Point X="222" Y="86" T="1302187830107" Pressure="128" />
		<Point X="225" Y="88" T="1302187830122" Pressure="128" />
		<Point X="227" Y="90" T="1302187830122" Pressure="128" />
		<Point X="228" Y="90" T="1302187830138" Pressure="128" />
		<Point X="230" Y="91" T="1302187830153" Pressure="128" />
		<Point X="231" Y="93" T="1302187830169" Pressure="128" />
		<Point X="229" Y="93" T="1302187830247" Pressure="128" />
		<Point X="228" Y="95" T="1302187830278" Pressure="128" />
		<Point X="227" Y="95" T="1302187830278" Pressure="128" />
		<Point X="225" Y="95" T="1302187830294" Pressure="128" />
		<Point X="223" Y="97" T="1302187830309" Pressure="128" />
		<Point X="220" Y="100" T="1302187830309" Pressure="128" />
		<Point X="217" Y="101" T="1302187830325" Pressure="128" />
		<Point X="214" Y="103" T="1302187830341" Pressure="128" />
		<Point X="210" Y="106" T="1302187830356" Pressure="128" />
		<Point X="206" Y="110" T="1302187830356" Pressure="128" />
		<Point X="201" Y="113" T="1302187830372" Pressure="128" />
		<Point X="195" Y="117" T="1302187830387" Pressure="128" />
		<Point X="189" Y="121" T="1302187830387" Pressure="128" />
		<Point X="183" Y="126" T="1302187830403" Pressure="128" />
		<Point X="177" Y="131" T="1302187830419" Pressure="128" />
		<Point X="171" Y="136" T="1302187830434" Pressure="128" />
		<Point X="166" Y="140" T="1302187830434" Pressure="128" />
		<Point X="161" Y="145" T="1302187830450" Pressure="128" />
		<Point X="156" Y="148" T="1302187830465" Pressure="128" />
		<Point X="151" Y="151" T="1302187830465" Pressure="128" />
		<Point X="147" Y="155" T="1302187830481" Pressure="128" />
		<Point X="144" Y="156" T="1302187830497" Pressure="128" />
		<Point X="142" Y="158" T="1302187830512" Pressure="128" />
		<Point X="140" Y="160" T="1302187830512" Pressure="128" />
		<Point X="138" Y="161" T="1302187830528" Pressure="128" />
		<Point X="137" Y="162" T="1302187830543" Pressure="128" />
		<Point X="137" Y="162" T="1302187830621" Pressure="128" />
	</Stroke>
</Gesture>
