<?xml version="1.0" encoding="utf-8" standalone="yes"?>
<Gesture Name="T~07" Subject="41" InputType="finger" Speed="FAST" NumPts="64">
	<Stroke index="1">
		<Point X="34" Y="26" T="1302212802596" Pressure="128" />
		<Point X="71" Y="23" T="1302212802596" Pressure="128" />
		<Point X="75" Y="23" T="1302212802612" Pressure="128" />
		<Point X="78" Y="22" T="1302212802627" Pressure="128" />
		<Point X="82" Y="22" T="1302212802627" Pressure="128" />
		<Point X="85" Y="22" T="1302212802643" Pressure="128" />
		<Point X="90" Y="22" T="1302212802658" Pressure="128" />
		<Point X="94" Y="22" T="1302212802674" Pressure="128" />
		<Point X="99" Y="22" T="1302212802674" Pressure="128" />
		<Point X="104" Y="22" T="1302212802690" Pressure="128" />
		<Point X="109" Y="21" T="1302212802705" Pressure="128" />
		<Point X="115" Y="21" T="1302212802705" Pressure="128" />
		<Point X="119" Y="21" T="1302212802721" Pressure="128" />
		<Point X="124" Y="21" T="1302212802736" Pressure="128" />
		<Point X="129" Y="21" T="1302212802736" Pressure="128" />
		<Point X="134" Y="21" T="1302212802752" Pressure="128" />
		<Point X="138" Y="21" T="1302212802768" Pressure="128" />
		<Point X="142" Y="21" T="1302212802783" Pressure="128" />
		<Point X="146" Y="21" T="1302212802783" Pressure="128" />
		<Point X="149" Y="21" T="1302212802799" Pressure="128" />
		<Point X="152" Y="21" T="1302212802814" Pressure="128" />
		<Point X="154" Y="21" T="1302212802814" Pressure="128" />
		<Point X="156" Y="21" T="1302212802830" Pressure="128" />
		<Point X="158" Y="21" T="1302212802846" Pressure="128" />
		<Point X="159" Y="21" T="1302212802861" Pressure="128" />
		<Point X="159" Y="21" T="1302212802892" Pressure="128" />
	</Stroke>
	<Stroke index="2">
		<Point X="108" Y="31" T="1302212804094" Pressure="128" />
		<Point X="112" Y="66" T="1302212804094" Pressure="128" />
		<Point X="113" Y="68" T="1302212804094" Pressure="128" />
		<Point X="113" Y="71" T="1302212804109" Pressure="128" />
		<Point X="113" Y="72" T="1302212804125" Pressure="128" />
		<Point X="113" Y="74" T="1302212804140" Pressure="128" />
		<Point X="113" Y="77" T="1302212804140" Pressure="128" />
		<Point X="113" Y="78" T="1302212804156" Pressure="128" />
		<Point X="113" Y="81" T="1302212804172" Pressure="128" />
		<Point X="113" Y="83" T="1302212804172" Pressure="128" />
		<Point X="113" Y="86" T="1302212804187" Pressure="128" />
		<Point X="113" Y="89" T="1302212804203" Pressure="128" />
		<Point X="115" Y="92" T="1302212804218" Pressure="128" />
		<Point X="115" Y="96" T="1302212804218" Pressure="128" />
		<Point X="115" Y="98" T="1302212804234" Pressure="128" />
		<Point X="115" Y="101" T="1302212804250" Pressure="128" />
		<Point X="115" Y="102" T="1302212804250" Pressure="128" />
		<Point X="115" Y="106" T="1302212804265" Pressure="128" />
		<Point X="115" Y="109" T="1302212804281" Pressure="128" />
		<Point X="115" Y="112" T="1302212804296" Pressure="128" />
		<Point X="115" Y="116" T="1302212804296" Pressure="128" />
		<Point X="115" Y="118" T="1302212804312" Pressure="128" />
		<Point X="115" Y="121" T="1302212804328" Pressure="128" />
		<Point X="115" Y="122" T="1302212804328" Pressure="128" />
		<Point X="116" Y="126" T="1302212804343" Pressure="128" />
		<Point X="116" Y="128" T="1302212804359" Pressure="128" />
		<Point X="116" Y="131" T="1302212804374" Pressure="128" />
		<Point X="116" Y="134" T="1302212804374" Pressure="128" />
		<Point X="116" Y="137" T="1302212804390" Pressure="128" />
		<Point X="117" Y="139" T="1302212804406" Pressure="128" />
		<Point X="117" Y="142" T="1302212804406" Pressure="128" />
		<Point X="117" Y="144" T="1302212804421" Pressure="128" />
		<Point X="117" Y="146" T="1302212804437" Pressure="128" />
		<Point X="117" Y="148" T="1302212804452" Pressure="128" />
		<Point X="117" Y="151" T="1302212804452" Pressure="128" />
		<Point X="117" Y="153" T="1302212804484" Pressure="128" />
		<Point X="117" Y="154" T="1302212804499" Pressure="128" />
		<Point X="117" Y="154" T="1302212804514" Pressure="128" />
	</Stroke>
</Gesture>
