<?xml version="1.0" encoding="utf-8" standalone="yes"?>
<Gesture Name="asterisk~10" Subject="73" InputType="finger" Speed="MEDIUM" NumPts="75">
	<Stroke index="1">
		<Point X="163" Y="23" T="1302187434069" Pressure="128" />
		<Point X="98" Y="64" T="1302187434069" Pressure="128" />
		<Point X="93" Y="69" T="1302187434069" Pressure="128" />
		<Point X="86" Y="74" T="1302187434084" Pressure="128" />
		<Point X="80" Y="78" T="1302187434100" Pressure="128" />
		<Point X="74" Y="83" T="1302187434100" Pressure="128" />
		<Point X="70" Y="86" T="1302187434116" Pressure="128" />
		<Point X="65" Y="89" T="1302187434131" Pressure="128" />
		<Point X="61" Y="93" T="1302187434147" Pressure="128" />
		<Point X="58" Y="95" T="1302187434147" Pressure="128" />
		<Point X="56" Y="98" T="1302187434162" Pressure="128" />
		<Point X="56" Y="98" T="1302187434178" Pressure="128" />
	</Stroke>
	<Stroke index="2">
		<Point X="60" Y="13" T="1302187434677" Pressure="128" />
		<Point X="105" Y="68" T="1302187434693" Pressure="128" />
		<Point X="110" Y="73" T="1302187434693" Pressure="128" />
		<Point X="113" Y="76" T="1302187434708" Pressure="128" />
		<Point X="118" Y="81" T="1302187434724" Pressure="128" />
		<Point X="121" Y="86" T="1302187434724" Pressure="128" />
		<Point X="125" Y="90" T="1302187434740" Pressure="128" />
		<Point X="128" Y="94" T="1302187434755" Pressure="128" />
		<Point X="131" Y="98" T="1302187434755" Pressure="128" />
		<Point X="135" Y="101" T="1302187434771" Pressure="128" />
		<Point X="136" Y="104" T="1302187434786" Pressure="128" />
		<Point X="139" Y="106" T="1302187434802" Pressure="128" />
		<Point X="140" Y="108" T="1302187434802" Pressure="128" />
		<Point X="141" Y="110" T="1302187434818" Pressure="128" />
		<Point X="143" Y="111" T="1302187434833" Pressure="128" />
		<Point X="143" Y="111" T="1302187434880" Pressure="128" />
	</Stroke>
	<Stroke index="3">
		<Point X="102" Y="3" T="1302187436783" Pressure="128" />
		<Point X="102" Y="40" T="1302187436783" Pressure="128" />
		<Point X="102" Y="43" T="1302187436799" Pressure="128" />
		<Point X="102" Y="44" T="1302187436814" Pressure="128" />
		<Point X="102" Y="48" T="1302187436814" Pressure="128" />
		<Point X="102" Y="49" T="1302187436830" Pressure="128" />
		<Point X="102" Y="53" T="1302187436846" Pressure="128" />
		<Point X="102" Y="54" T="1302187436846" Pressure="128" />
		<Point X="102" Y="58" T="1302187436861" Pressure="128" />
		<Point X="102" Y="60" T="1302187436877" Pressure="128" />
		<Point X="102" Y="61" T="1302187436892" Pressure="128" />
		<Point X="102" Y="63" T="1302187436892" Pressure="128" />
		<Point X="102" Y="65" T="1302187436908" Pressure="128" />
		<Point X="102" Y="68" T="1302187436924" Pressure="128" />
		<Point X="101" Y="70" T="1302187436924" Pressure="128" />
		<Point X="101" Y="73" T="1302187436939" Pressure="128" />
		<Point X="101" Y="74" T="1302187436955" Pressure="128" />
		<Point X="101" Y="76" T="1302187436970" Pressure="128" />
		<Point X="101" Y="79" T="1302187436970" Pressure="128" />
		<Point X="101" Y="80" T="1302187436986" Pressure="128" />
		<Point X="101" Y="83" T="1302187437002" Pressure="128" />
		<Point X="100" Y="84" T="1302187437002" Pressure="128" />
		<Point X="100" Y="86" T="1302187437017" Pressure="128" />
		<Point X="100" Y="88" T="1302187437033" Pressure="128" />
		<Point X="100" Y="90" T="1302187437048" Pressure="128" />
		<Point X="100" Y="93" T="1302187437048" Pressure="128" />
		<Point X="100" Y="94" T="1302187437064" Pressure="128" />
		<Point X="100" Y="95" T="1302187437080" Pressure="128" />
		<Point X="100" Y="98" T="1302187437080" Pressure="128" />
		<Point X="100" Y="99" T="1302187437095" Pressure="128" />
		<Point X="100" Y="101" T="1302187437111" Pressure="128" />
		<Point X="100" Y="103" T="1302187437126" Pressure="128" />
		<Point X="100" Y="104" T="1302187437126" Pressure="128" />
		<Point X="100" Y="106" T="1302187437142" Pressure="128" />
		<Point X="100" Y="108" T="1302187437158" Pressure="128" />
		<Point X="100" Y="110" T="1302187437158" Pressure="128" />
		<Point X="100" Y="113" T="1302187437173" Pressure="128" />
		<Point X="100" Y="114" T="1302187437189" Pressure="128" />
		<Point X="100" Y="116" T="1302187437204" Pressure="128" />
		<Point X="100" Y="118" T="1302187437204" Pressure="128" />
		<Point X="100" Y="120" T="1302187437220" Pressure="128" />
		<Point X="100" Y="123" T="1302187437236" Pressure="128" />
		<Point X="100" Y="124" T="1302187437251" Pressure="128" />
		<Point X="100" Y="126" T="1302187437267" Pressure="128" />
		<Point X="101" Y="128" T="1302187437282" Pressure="128" />
		<Point X="101" Y="129" T="1302187437314" Pressure="128" />
		<Point X="101" Y="129" T="1302187437345" Pressure="128" />
	</Stroke>
</Gesture>
