<?xml version="1.0" encoding="utf-8" standalone="yes"?>
<Gesture Name="question_mark02" Subject="7" Speed="slow" Number="2" NumPts="60" Millseconds="714" AppName="Gestures" AppVer="3.7.0.0" Date="Sunday, March 11, 2007" TimeOfDay="1:38:14 PM">
  <Point X="88" Y="183" T="122787346" />
  <Point X="86" Y="181" T="122787378" />
  <Point X="84" Y="179" T="122787399" />
  <Point X="82" Y="178" T="122787415" />
  <Point X="81" Y="175" T="122787427" />
  <Point X="81" Y="173" T="122787436" />
  <Point X="80" Y="171" T="122787444" />
  <Point X="79" Y="169" T="122787452" />
  <Point X="78" Y="166" T="122787464" />
  <Point X="78" Y="164" T="122787472" />
  <Point X="77" Y="161" T="122787480" />
  <Point X="77" Y="158" T="122787488" />
  <Point X="77" Y="156" T="122787496" />
  <Point X="77" Y="154" T="122787505" />
  <Point X="77" Y="151" T="122787513" />
  <Point X="78" Y="149" T="122787524" />
  <Point X="79" Y="147" T="122787532" />
  <Point X="81" Y="144" T="122787544" />
  <Point X="82" Y="141" T="122787553" />
  <Point X="85" Y="139" T="122787561" />
  <Point X="87" Y="137" T="122787571" />
  <Point X="89" Y="136" T="122787580" />
  <Point X="92" Y="135" T="122787589" />
  <Point X="95" Y="133" T="122787599" />
  <Point X="98" Y="131" T="122787600" />
  <Point X="102" Y="130" T="122787611" />
  <Point X="107" Y="128" T="122787621" />
  <Point X="111" Y="127" T="122787632" />
  <Point X="113" Y="128" T="122787633" />
  <Point X="117" Y="128" T="122787644" />
  <Point X="121" Y="127" T="122787655" />
  <Point X="124" Y="127" T="122787656" />
  <Point X="127" Y="129" T="122787668" />
  <Point X="130" Y="129" T="122787680" />
  <Point X="132" Y="131" T="122787681" />
  <Point X="134" Y="133" T="122787693" />
  <Point X="138" Y="138" T="122787706" />
  <Point X="139" Y="141" T="122787719" />
  <Point X="141" Y="147" T="122787732" />
  <Point X="141" Y="153" T="122787746" />
  <Point X="141" Y="157" T="122787759" />
  <Point X="139" Y="163" T="122787773" />
  <Point X="137" Y="167" T="122787787" />
  <Point X="135" Y="174" T="122787801" />
  <Point X="132" Y="176" T="122787815" />
  <Point X="128" Y="181" T="122787829" />
  <Point X="124" Y="186" T="122787847" />
  <Point X="120" Y="190" T="122787861" />
  <Point X="117" Y="194" T="122787877" />
  <Point X="114" Y="198" T="122787892" />
  <Point X="111" Y="203" T="122787907" />
  <Point X="110" Y="209" T="122787923" />
  <Point X="109" Y="215" T="122787939" />
  <Point X="109" Y="221" T="122787956" />
  <Point X="110" Y="227" T="122787973" />
  <Point X="112" Y="233" T="122787990" />
  <Point X="115" Y="239" T="122788007" />
  <Point X="119" Y="244" T="122788024" />
  <Point X="122" Y="248" T="122788042" />
  <Point X="124" Y="250" T="122788060" />
</Gesture>